pytest_forked/__init__.py
pytest_forked-1.6.0.dist-info/LICENSE
pytest_forked-1.6.0.dist-info/METADATA
pytest_forked-1.6.0.dist-info/WHEEL
pytest_forked-1.6.0.dist-info/entry_points.txt
pytest_forked-1.6.0.dist-info/top_level.txt
pytest_forked-1.6.0.dist-info/RECORD
